gaia_density.py
gaia_density-0.0.1.dist-info/licenses/LICENSE
gaia_density-0.0.1.dist-info/METADATA
gaia_density-0.0.1.dist-info/WHEEL
gaia_density-0.0.1.dist-info/top_level.txt
gaia_density-0.0.1.dist-info/RECORD
